[{"first_name": "RICHARD M", "last_name": "BURR", "office": "Senator", "ptr_link": "https://efdsearch.senate.gov/search/view/paper/e787a949-dba2-4b49-8d97-c27a8afce004/", "date_recieved": "05/01/2018", "transactions": []}, {"first_name": "Thomas R", "last_name": "Carper", "office": "Carper, Thomas R. (Senator)", "ptr_link": "https://efdsearch.senate.gov/search/view/ptr/cea4055c-8230-4f46-8076-802a1750c886/", "date_recieved": "05/01/2018", "transactions": [{"transaction_date": "04/16/2018", "owner": "Spouse", "ticker": "--", "asset_description": "International Lease Finance <div class=\"text-muted\"><em>Rate/Coupon:</em> 3.875%<br> <em>Matures:</em> 04/15/2018</div>", "asset_type": "Corporate Bond", "type": "Sale (Full)", "amount": "$1,001 - $15,000", "comment": "--"}, {"transaction_date": "04/13/2018", "owner": "Spouse", "ticker": "--", "asset_description": "Dominion Energy <div class=\"text-muted\"><em>Rate/Coupon:</em> 2.579%<br> <em>Matures:</em> 07/01/2020</div>", "asset_type": "Corporate Bond", "type": "Purchase", "amount": "$1,001 - $15,000", "comment": "--"}]}, {"first_name": "David A", "last_name": "Perdue , Jr", "office": "Perdue, David (Senator)", "ptr_link": "https://efdsearch.senate.gov/search/view/ptr/07163d2f-2ddf-4e81-a2b4-210fb8a469d2/", "date_recieved": "05/01/2018", "transactions": [{"transaction_date": "04/27/2018", "owner": "Joint", "ticker": "<a href=\"https://finance.yahoo.com/q?s=USG\" target=\"_blank\">USG</a>", "asset_description": "USG Corporation", "asset_type": "Stock", "type": "Sale (Partial)", "amount": "$1,001 - $15,000", "comment": "--"}, {"transaction_date": "04/26/2018", "owner": "Joint", "ticker": "<a href=\"https://finance.yahoo.com/q?s=USG\" target=\"_blank\">USG</a>", "asset_description": "USG Corporation", "asset_type": "Stock", "type": "Sale (Partial)", "amount": "$1,001 - $15,000", "comment": "--"}, {"transaction_date": "04/26/2018", "owner": "Joint", "ticker": "<a href=\"https://finance.yahoo.com/q?s=WPX\" target=\"_blank\">WPX</a>", "asset_description": "WPX Energy, Inc.", "asset_type": "Stock", "type": "Sale (Partial)", "amount": "$1,001 - $15,000", "comment": "--"}, {"transaction_date": "04/25/2018", "owner": "Joint", "ticker": "<a href=\"https://finance.yahoo.com/q?s=GLW\" target=\"_blank\">GLW</a>", "asset_description": "Corning Incorporated", "asset_type": "Stock", "type": "Purchase", "amount": "$1,001 - $15,000", "comment": "--"}, {"transaction_date": "04/24/2018", "owner": "Joint", "ticker": "<a href=\"https://finance.yahoo.com/q?s=C\" target=\"_blank\">C</a>", "asset_description": "Citigroup Inc.", "asset_type": "Stock", "type": "Purchase", "amount": "$1,001 - $15,000", "comment": "--"}, {"transaction_date": "04/24/2018", "owner": "Joint", "ticker": "<a href=\"https://finance.yahoo.com/q?s=GIS\" target=\"_blank\">GIS</a>", "asset_description": "General Mills, Inc.", "asset_type": "Stock", "type": "Purchase", "amount": "$1,001 - $15,000", "comment": "--"}, {"transaction_date": "04/24/2018", "owner": "Joint", "ticker": "<a href=\"https://finance.yahoo.com/q?s=MRK\" target=\"_blank\">MRK</a>", "asset_description": "Merck &amp; Co., Inc.", "asset_type": "Stock", "type": "Purchase", "amount": "$1,001 - $15,000", "comment": "--"}, {"transaction_date": "04/20/2018", "owner": "Joint", "ticker": "<a href=\"https://finance.yahoo.com/q?s=CLX\" target=\"_blank\">CLX</a>", "asset_description": "The Clorox Company", "asset_type": "Stock", "type": "Purchase", "amount": "$1,001 - $15,000", "comment": "--"}, {"transaction_date": "04/20/2018", "owner": "Joint", "ticker": "<a href=\"https://finance.yahoo.com/q?s=PG\" target=\"_blank\">PG</a>", "asset_description": "The Procter &amp; Gamble Company", "asset_type": "Stock", "type": "Purchase", "amount": "$15,001 - $50,000", "comment": "--"}, {"transaction_date": "04/20/2018", "owner": "Joint", "ticker": "<a href=\"https://finance.yahoo.com/q?s=PEP\" target=\"_blank\">PEP</a>", "asset_description": "PepsiCo, Inc.", "asset_type": "Stock", "type": "Purchase", "amount": "$15,001 - $50,000", "comment": "--"}, {"transaction_date": "04/17/2018", "owner": "Joint", "ticker": "<a href=\"https://finance.yahoo.com/q?s=DUK\" target=\"_blank\">DUK</a>", "asset_description": "Duke Energy Corporation", "asset_type": "Stock", "type": "Sale (Full)", "amount": "$15,001 - $50,000", "comment": "--"}, {"transaction_date": "04/13/2018", "owner": "Joint", "ticker": "<a href=\"https://finance.yahoo.com/q?s=USG\" target=\"_blank\">USG</a>", "asset_description": "USG Corporation", "asset_type": "Stock", "type": "Sale (Partial)", "amount": "$1,001 - $15,000", "comment": "--"}, {"transaction_date": "04/12/2018", "owner": "Joint", "ticker": "<a href=\"https://finance.yahoo.com/q?s=USG\" target=\"_blank\">USG</a>", "asset_description": "USG Corporation", "asset_type": "Stock", "type": "Sale (Partial)", "amount": "$1,001 - $15,000", "comment": "--"}, {"transaction_date": "04/09/2018", "owner": "Joint", "ticker": "<a href=\"https://finance.yahoo.com/q?s=USG\" target=\"_blank\">USG</a>", "asset_description": "USG Corporation", "asset_type": "Stock", "type": "Sale (Partial)", "amount": "$1,001 - $15,000", "comment": "--"}]}]