[{"first_name": "Mark R", "last_name": "Warner", "office": "Warner, Mark (Senator)", "ptr_link": "https://efdsearch.senate.gov/search/view/ptr/4eedb755-716b-4b3d-9b5c-26bcca095138/", "date_recieved": "06/09/2020", "transactions": [{"transaction_date": "05/04/2020", "owner": "Self", "ticker": "--", "asset_description": "BetterCloud <div class=\"text-muted\"> <em>Company:</em> BetterCloud &nbsp;(New York, NY) </div> <div class=\"text-muted\"><em>Description:</em>&nbsp;Cloud Storage</div>", "asset_type": "Other Securities", "type": "Purchase", "amount": "$250,001 - $500,000", "comment": "Underlying asset of New Amsterdam BC Investors, LLC"}], "bioguide": "W000805"}]