[{"first_name": "Angus S", "last_name": "King, Jr.", "office": "King, Angus (Senator)", "ptr_link": "https://efdsearch.senate.gov/search/view/ptr/8b901467-872e-4963-96fa-a5cef2760fa2/", "date_recieved": "06/17/2019", "transactions": [{"transaction_date": "05/16/2019", "owner": "Spouse", "ticker": "--", "asset_description": "MAINE ST HSG AUTH REV BOND <div class=\"text-muted\"><em>Rate/Coupon:</em> 1.70%<br> <em>Matures:</em> 11/15/2021</div>", "asset_type": "Municipal Security", "type": "Purchase", "amount": "$15,001 - $50,000", "comment": "--"}], "bioguide": "K000383"}]