[{"first_name": "Ron L", "last_name": "Wyden", "office": "Wyden, Ron (Senator)", "ptr_link": "https://efdsearch.senate.gov/search/view/ptr/33782dc2-cf18-4f2f-82c3-64d6e9572596/", "date_recieved": "08/29/2020", "transactions": [{"transaction_date": "08/20/2020", "owner": "Child", "ticker": "<a href=\"https://finance.yahoo.com/q?s=NFLX\" target=\"_blank\">NFLX</a>", "asset_description": "Netflix, Inc.", "asset_type": "Stock", "type": "Purchase", "amount": "$1,001 - $15,000", "comment": "Underlying asset of dependent child #3"}, {"transaction_date": "08/20/2020", "owner": "Child", "ticker": "<a href=\"https://finance.yahoo.com/q?s=NFLX\" target=\"_blank\">NFLX</a>", "asset_description": "Netflix, Inc.", "asset_type": "Stock", "type": "Purchase", "amount": "$1,001 - $15,000", "comment": "Underlying asset of dependent child #2"}, {"transaction_date": "08/20/2020", "owner": "Child", "ticker": "<a href=\"https://finance.yahoo.com/q?s=NFLX\" target=\"_blank\">NFLX</a>", "asset_description": "Netflix, Inc.", "asset_type": "Stock", "type": "Purchase", "amount": "$1,001 - $15,000", "comment": "Underlying asset of dependent child #1"}, {"transaction_date": "08/21/2020", "owner": "Spouse", "ticker": "<a href=\"https://finance.yahoo.com/q?s=NVDA\" target=\"_blank\">NVDA</a>", "asset_description": "NVIDIA Corporation", "asset_type": "Stock", "type": "Purchase", "amount": "$50,001 - $100,000", "comment": "--"}, {"transaction_date": "08/21/2020", "owner": "Spouse", "ticker": "<a href=\"https://finance.yahoo.com/q?s=UPS\" target=\"_blank\">UPS</a>", "asset_description": "United Parcel Service, Inc.", "asset_type": "Stock", "type": "Purchase", "amount": "$50,001 - $100,000", "comment": "--"}, {"transaction_date": "08/21/2020", "owner": "Spouse", "ticker": "<a href=\"https://finance.yahoo.com/q?s=FDX\" target=\"_blank\">FDX</a>", "asset_description": "FedEx Corporation", "asset_type": "Stock", "type": "Purchase", "amount": "$15,001 - $50,000", "comment": "--"}, {"transaction_date": "08/21/2020", "owner": "Spouse", "ticker": "<a href=\"https://finance.yahoo.com/q?s=SQ\" target=\"_blank\">SQ</a>", "asset_description": "Square, Inc.", "asset_type": "Stock", "type": "Purchase", "amount": "$15,001 - $50,000", "comment": "--"}, {"transaction_date": "08/21/2020", "owner": "Spouse", "ticker": "<a href=\"https://finance.yahoo.com/q?s=T\" target=\"_blank\">T</a>", "asset_description": "AT&amp;T Inc.", "asset_type": "Stock", "type": "Sale (Full)", "amount": "$50,001 - $100,000", "comment": "--"}, {"transaction_date": "08/21/2020", "owner": "Spouse", "ticker": "<a href=\"https://finance.yahoo.com/q?s=XOM\" target=\"_blank\">XOM</a>", "asset_description": "Exxon Mobil Corporation", "asset_type": "Stock", "type": "Sale (Full)", "amount": "$15,001 - $50,000", "comment": "--"}, {"transaction_date": "08/19/2020", "owner": "Spouse", "ticker": "<a href=\"https://finance.yahoo.com/q?s=UPS\" target=\"_blank\">UPS</a>", "asset_description": "United Parcel Service, Inc.", "asset_type": "Stock", "type": "Purchase", "amount": "$50,001 - $100,000", "comment": "--"}, {"transaction_date": "08/19/2020", "owner": "Spouse", "ticker": "<a href=\"https://finance.yahoo.com/q?s=NVDA\" target=\"_blank\">NVDA</a>", "asset_description": "NVIDIA Corporation", "asset_type": "Stock", "type": "Purchase", "amount": "$15,001 - $50,000", "comment": "--"}, {"transaction_date": "08/19/2020", "owner": "Spouse", "ticker": "<a href=\"https://finance.yahoo.com/q?s=KR\" target=\"_blank\">KR</a>", "asset_description": "The Kroger Co.", "asset_type": "Stock", "type": "Purchase", "amount": "$15,001 - $50,000", "comment": "--"}, {"transaction_date": "08/19/2020", "owner": "Spouse", "ticker": "<a href=\"https://finance.yahoo.com/q?s=FDX\" target=\"_blank\">FDX</a>", "asset_description": "FedEx Corporation", "asset_type": "Stock", "type": "Purchase", "amount": "$15,001 - $50,000", "comment": "--"}, {"transaction_date": "08/18/2020", "owner": "Spouse", "ticker": "<a href=\"https://finance.yahoo.com/q?s=LOW\" target=\"_blank\">LOW</a>", "asset_description": "Lowe's Companies, Inc.", "asset_type": "Stock", "type": "Purchase", "amount": "$15,001 - $50,000", "comment": "--"}, {"transaction_date": "08/18/2020", "owner": "Spouse", "ticker": "<a href=\"https://finance.yahoo.com/q?s=DHI\" target=\"_blank\">DHI</a>", "asset_description": "D.R. Horton, Inc.", "asset_type": "Stock", "type": "Purchase", "amount": "$15,001 - $50,000", "comment": "--"}, {"transaction_date": "08/17/2020", "owner": "Spouse", "ticker": "<a href=\"https://finance.yahoo.com/q?s=UPS\" target=\"_blank\">UPS</a>", "asset_description": "United Parcel Service, Inc.", "asset_type": "Stock", "type": "Purchase", "amount": "$50,001 - $100,000", "comment": "--"}, {"transaction_date": "08/14/2020", "owner": "Spouse", "ticker": "<a href=\"https://finance.yahoo.com/q?s=UPS\" target=\"_blank\">UPS</a>", "asset_description": "United Parcel Service, Inc.", "asset_type": "Stock", "type": "Purchase", "amount": "$15,001 - $50,000", "comment": "--"}, {"transaction_date": "08/14/2020", "owner": "Spouse", "ticker": "<a href=\"https://finance.yahoo.com/q?s=PSA\" target=\"_blank\">PSA</a>", "asset_description": "Public Storage", "asset_type": "Stock", "type": "Purchase", "amount": "$15,001 - $50,000", "comment": "--"}, {"transaction_date": "08/14/2020", "owner": "Spouse", "ticker": "<a href=\"https://finance.yahoo.com/q?s=FDX\" target=\"_blank\">FDX</a>", "asset_description": "FedEx Corporation", "asset_type": "Stock", "type": "Purchase", "amount": "$15,001 - $50,000", "comment": "--"}, {"transaction_date": "08/11/2020", "owner": "Spouse", "ticker": "<a href=\"https://finance.yahoo.com/q?s=F\" target=\"_blank\">F</a>", "asset_description": "Ford Motor Company", "asset_type": "Stock", "type": "Purchase", "amount": "$15,001 - $50,000", "comment": "--"}, {"transaction_date": "08/11/2020", "owner": "Spouse", "ticker": "<a href=\"https://finance.yahoo.com/q?s=DHI\" target=\"_blank\">DHI</a>", "asset_description": "D.R. Horton, Inc.", "asset_type": "Stock", "type": "Purchase", "amount": "$50,001 - $100,000", "comment": "--"}, {"transaction_date": "08/07/2020", "owner": "Spouse", "ticker": "<a href=\"https://finance.yahoo.com/q?s=AAPL\" target=\"_blank\">AAPL</a>", "asset_description": "Apple Inc.", "asset_type": "Stock", "type": "Purchase", "amount": "$50,001 - $100,000", "comment": "--"}, {"transaction_date": "08/05/2020", "owner": "Spouse", "ticker": "<a href=\"https://finance.yahoo.com/q?s=WDAY\" target=\"_blank\">WDAY</a>", "asset_description": "Workday, Inc.", "asset_type": "Stock", "type": "Purchase", "amount": "$1,001 - $15,000", "comment": "--"}, {"transaction_date": "08/05/2020", "owner": "Spouse", "ticker": "<a href=\"https://finance.yahoo.com/q?s=PSA\" target=\"_blank\">PSA</a>", "asset_description": "Public Storage", "asset_type": "Stock", "type": "Purchase", "amount": "$15,001 - $50,000", "comment": "--"}, {"transaction_date": "08/05/2020", "owner": "Spouse", "ticker": "<a href=\"https://finance.yahoo.com/q?s=KR\" target=\"_blank\">KR</a>", "asset_description": "The Kroger Co.", "asset_type": "Stock", "type": "Purchase", "amount": "$1,001 - $15,000", "comment": "--"}, {"transaction_date": "08/05/2020", "owner": "Spouse", "ticker": "<a href=\"https://finance.yahoo.com/q?s=DHI\" target=\"_blank\">DHI</a>", "asset_description": "D.R. Horton, Inc.", "asset_type": "Stock", "type": "Purchase", "amount": "$1,001 - $15,000", "comment": "--"}, {"transaction_date": "08/05/2020", "owner": "Spouse", "ticker": "<a href=\"https://finance.yahoo.com/q?s=COUP\" target=\"_blank\">COUP</a>", "asset_description": "Coupa Software Incorporated", "asset_type": "Stock", "type": "Purchase", "amount": "$15,001 - $50,000", "comment": "--"}, {"transaction_date": "08/05/2020", "owner": "Spouse", "ticker": "<a href=\"https://finance.yahoo.com/q?s=CLX\" target=\"_blank\">CLX</a>", "asset_description": "The Clorox Company", "asset_type": "Stock", "type": "Purchase", "amount": "$1,001 - $15,000", "comment": "--"}, {"transaction_date": "08/05/2020", "owner": "Spouse", "ticker": "<a href=\"https://finance.yahoo.com/q?s=BYND\" target=\"_blank\">BYND</a>", "asset_description": "Beyond Meat, Inc.", "asset_type": "Stock", "type": "Purchase", "amount": "$15,001 - $50,000", "comment": "--"}, {"transaction_date": "08/04/2020", "owner": "Spouse", "ticker": "<a href=\"https://finance.yahoo.com/q?s=PSA\" target=\"_blank\">PSA</a>", "asset_description": "Public Storage", "asset_type": "Stock", "type": "Purchase", "amount": "$50,001 - $100,000", "comment": "--"}, {"transaction_date": "08/04/2020", "owner": "Spouse", "ticker": "<a href=\"https://finance.yahoo.com/q?s=MTCH\" target=\"_blank\">MTCH</a>", "asset_description": "Match Group, Inc.", "asset_type": "Stock", "type": "Purchase", "amount": "$1,001 - $15,000", "comment": "--"}, {"transaction_date": "08/04/2020", "owner": "Spouse", "ticker": "<a href=\"https://finance.yahoo.com/q?s=KR\" target=\"_blank\">KR</a>", "asset_description": "The Kroger Co.", "asset_type": "Stock", "type": "Purchase", "amount": "$1,001 - $15,000", "comment": "--"}, {"transaction_date": "08/04/2020", "owner": "Spouse", "ticker": "<a href=\"https://finance.yahoo.com/q?s=KLAC\" target=\"_blank\">KLAC</a>", "asset_description": "KLA Corporation", "asset_type": "Stock", "type": "Purchase", "amount": "$15,001 - $50,000", "comment": "--"}, {"transaction_date": "08/04/2020", "owner": "Spouse", "ticker": "<a href=\"https://finance.yahoo.com/q?s=DIS\" target=\"_blank\">DIS</a>", "asset_description": "The Walt Disney Company", "asset_type": "Stock", "type": "Purchase", "amount": "$15,001 - $50,000", "comment": "--"}, {"transaction_date": "08/03/2020", "owner": "Spouse", "ticker": "<a href=\"https://finance.yahoo.com/q?s=MAR\" target=\"_blank\">MAR</a>", "asset_description": "Marriott International, Inc.", "asset_type": "Stock", "type": "Sale (Full)", "amount": "$100,001 - $250,000", "comment": "--"}, {"transaction_date": "08/03/2020", "owner": "Spouse", "ticker": "<a href=\"https://finance.yahoo.com/q?s=VAC\" target=\"_blank\">VAC</a>", "asset_description": "Marriott Vacations Worldwide Corporation", "asset_type": "Stock", "type": "Sale (Full)", "amount": "$15,001 - $50,000", "comment": "--"}, {"transaction_date": "08/03/2020", "owner": "Spouse", "ticker": "<a href=\"https://finance.yahoo.com/q?s=INTC\" target=\"_blank\">INTC</a>", "asset_description": "Intel Corporation", "asset_type": "Stock", "type": "Sale (Full)", "amount": "$15,001 - $50,000", "comment": "--"}, {"transaction_date": "07/31/2020", "owner": "Spouse", "ticker": "<a href=\"https://finance.yahoo.com/q?s=MSFT\" target=\"_blank\">MSFT</a>", "asset_description": "Microsoft Corporation", "asset_type": "Stock", "type": "Purchase", "amount": "$50,001 - $100,000", "comment": "--"}, {"transaction_date": "07/30/2020", "owner": "Spouse", "ticker": "<a href=\"https://finance.yahoo.com/q?s=OSK\" target=\"_blank\">OSK</a>", "asset_description": "Oshkosh Corporation", "asset_type": "Stock", "type": "Purchase", "amount": "$15,001 - $50,000", "comment": "--"}, {"transaction_date": "07/30/2020", "owner": "Spouse", "ticker": "<a href=\"https://finance.yahoo.com/q?s=NVDA\" target=\"_blank\">NVDA</a>", "asset_description": "NVIDIA Corporation", "asset_type": "Stock", "type": "Purchase", "amount": "$50,001 - $100,000", "comment": "--"}, {"transaction_date": "07/30/2020", "owner": "Spouse", "ticker": "<a href=\"https://finance.yahoo.com/q?s=BYND\" target=\"_blank\">BYND</a>", "asset_description": "Beyond Meat, Inc.", "asset_type": "Stock", "type": "Purchase", "amount": "$15,001 - $50,000", "comment": "--"}], "bioguide": "W000779"}]