[{"first_name": "Angus S", "last_name": "King, Jr.", "office": "King, Angus (Senator)", "ptr_link": "https://efdsearch.senate.gov/search/view/ptr/7dd32f76-2862-421d-b105-84ff6a5e01cd/", "date_recieved": "11/10/2016", "transactions": [{"transaction_date": "10/19/2016", "owner": "Spouse", "ticker": "<a href=\"https://finance.yahoo.com/q?s=TEVA\" target=\"_blank\">TEVA</a>", "asset_description": "Teva Pharmaceutical Industries Limited", "asset_type": "Stock", "type": "Sale (Full)", "amount": "$1,001 - $15,000", "comment": "--"}, {"transaction_date": "10/19/2016", "owner": "Spouse", "ticker": "<a href=\"https://finance.yahoo.com/q?s=GE\" target=\"_blank\">GE</a>", "asset_description": "General Electric Company", "asset_type": "Stock", "type": "Sale (Full)", "amount": "$1,001 - $15,000", "comment": "--"}], "bioguide": "K000383"}]