[{"first_name": "Susan M", "last_name": "Collins", "office": "Collins, Susan M. (Senator)", "ptr_link": "https://efdsearch.senate.gov/search/view/ptr/614f837e-4d49-459b-b50b-1e6cdd90d212/", "date_recieved": "02/14/2017", "transactions": [{"transaction_date": "01/31/2017", "owner": "Spouse", "ticker": "--", "asset_description": "Federal Farm Credit Bank 3133EGU94 <div class=\"text-muted\"><em>Rate/Coupon:</em> 2.300%<br> <em>Matures:</em> 12/14/2022</div>", "asset_type": "Corporate Bond", "type": "Purchase", "amount": "$15,001 - $50,000", "comment": "--"}]}, {"first_name": "Sheldon", "last_name": "Whitehouse", "office": "Whitehouse, Sheldon (Senator)", "ptr_link": "https://efdsearch.senate.gov/search/view/ptr/18f07909-0ca6-4804-8503-d83c0b84a15e/", "date_recieved": "02/14/2017", "transactions": [{"transaction_date": "01/11/2017", "owner": "Child", "ticker": "<a href=\"https://finance.yahoo.com/q?s=MDT\" target=\"_blank\">MDT</a>", "asset_description": "Medtronic plc", "asset_type": "Stock", "type": "Sale (Full)", "amount": "$1,001 - $15,000", "comment": "--"}, {"transaction_date": "01/11/2017", "owner": "Spouse", "ticker": "<a href=\"https://finance.yahoo.com/q?s=NVDA\" target=\"_blank\">NVDA</a>", "asset_description": "NVIDIA Corporation", "asset_type": "Stock", "type": "Purchase", "amount": "$1,001 - $15,000", "comment": "--"}, {"transaction_date": "01/11/2017", "owner": "Spouse", "ticker": "<a href=\"https://finance.yahoo.com/q?s=PANW\" target=\"_blank\">PANW</a>", "asset_description": "Palo Alto Networks, Inc.", "asset_type": "Stock", "type": "Sale (Full)", "amount": "$1,001 - $15,000", "comment": "--"}, {"transaction_date": "01/11/2017", "owner": "Joint", "ticker": "<a href=\"https://finance.yahoo.com/q?s=UNH\" target=\"_blank\">UNH</a>", "asset_description": "UnitedHealth Group Incorporated", "asset_type": "Stock", "type": "Sale (Partial)", "amount": "$15,001 - $50,000", "comment": "--"}, {"transaction_date": "01/11/2017", "owner": "Joint", "ticker": "<a href=\"https://finance.yahoo.com/q?s=PANW\" target=\"_blank\">PANW</a>", "asset_description": "Palo Alto Networks, Inc.", "asset_type": "Stock", "type": "Sale (Full)", "amount": "$1,001 - $15,000", "comment": "--"}, {"transaction_date": "01/11/2017", "owner": "Joint", "ticker": "<a href=\"https://finance.yahoo.com/q?s=AAPL\" target=\"_blank\">AAPL</a>", "asset_description": "Apple Inc.", "asset_type": "Stock", "type": "Sale (Partial)", "amount": "$1,001 - $15,000", "comment": "--"}, {"transaction_date": "01/11/2017", "owner": "Joint", "ticker": "<a href=\"https://finance.yahoo.com/q?s=NSRGY\" target=\"_blank\">NSRGY</a>", "asset_description": "Nestl\u00e9 S.A.", "asset_type": "Stock", "type": "Sale (Partial)", "amount": "$15,001 - $50,000", "comment": "--"}, {"transaction_date": "01/24/2017", "owner": "Joint", "ticker": "<a href=\"https://finance.yahoo.com/q?s=TMUS\" target=\"_blank\">TMUS</a>", "asset_description": "T-Mobile US, Inc.", "asset_type": "Stock", "type": "Purchase", "amount": "$15,001 - $50,000", "comment": "--"}, {"transaction_date": "01/24/2017", "owner": "Joint", "ticker": "<a href=\"https://finance.yahoo.com/q?s=IR\" target=\"_blank\">IR</a>", "asset_description": "Ingersoll-Rand Plc", "asset_type": "Stock", "type": "Purchase", "amount": "$15,001 - $50,000", "comment": "--"}, {"transaction_date": "01/24/2017", "owner": "Joint", "ticker": "<a href=\"https://finance.yahoo.com/q?s=BA\" target=\"_blank\">BA</a>", "asset_description": "The Boeing Company", "asset_type": "Stock", "type": "Purchase", "amount": "$1,001 - $15,000", "comment": "--"}, {"transaction_date": "01/30/2017", "owner": "Joint", "ticker": "<a href=\"https://finance.yahoo.com/q?s=MO\" target=\"_blank\">MO</a>", "asset_description": "MO-Altria Group, Inc.", "asset_type": "Stock", "type": "Sale (Full)", "amount": "$1,001 - $15,000", "comment": "Acquired as a result of a 9/21/16 inheritance"}, {"transaction_date": "01/30/2017", "owner": "Joint", "ticker": "<a href=\"https://finance.yahoo.com/q?s=LW\" target=\"_blank\">LW</a>", "asset_description": "LW-Lamb Weston Holdings, Inc.", "asset_type": "Stock", "type": "Sale (Full)", "amount": "$1,001 - $15,000", "comment": "LW received as a split from CAG on 11/09/16"}, {"transaction_date": "01/11/2017", "owner": "Self", "ticker": "<a href=\"https://finance.yahoo.com/q?s=AAPL\" target=\"_blank\">AAPL</a>", "asset_description": "Apple Inc.", "asset_type": "Stock", "type": "Sale (Partial)", "amount": "$15,001 - $50,000", "comment": "--"}, {"transaction_date": "01/25/2017", "owner": "Self", "ticker": "<a href=\"https://finance.yahoo.com/q?s=IR\" target=\"_blank\">IR</a>", "asset_description": "Ingersoll-Rand Plc", "asset_type": "Stock", "type": "Purchase", "amount": "$15,001 - $50,000", "comment": "--"}, {"transaction_date": "01/30/2017", "owner": "Self", "ticker": "<a href=\"https://finance.yahoo.com/q?s=MO\" target=\"_blank\">MO</a>", "asset_description": "Altria Group, Inc.", "asset_type": "Stock", "type": "Sale (Full)", "amount": "$15,001 - $50,000", "comment": "--"}, {"transaction_date": "01/25/2017", "owner": "Self", "ticker": "<a href=\"https://finance.yahoo.com/q?s=USB\" target=\"_blank\">USB</a>", "asset_description": "U.S. Bancorp", "asset_type": "Stock", "type": "Purchase", "amount": "$1,001 - $15,000", "comment": "--"}, {"transaction_date": "01/30/2017", "owner": "Self", "ticker": "<a href=\"https://finance.yahoo.com/q?s=BRK-B\" target=\"_blank\">BRK-B</a>", "asset_description": "Berkshire Hathaway Inc.", "asset_type": "Stock", "type": "Purchase", "amount": "$1,001 - $15,000", "comment": "--"}]}]